{
  "swagger": "2.0",
  "info": {
    "title": "MoodleConnector",
    "description": "Connect to Moodle webservices with this custom connector",
    "version": "1.0"
  },
  "host": "university.catalyst-au.net",
  "basePath": "/",
  "schemes": [
    "https"
  ],
  "consumes": [],
  "produces": [],
  "paths": {
    "/moodle/webservice/rest/server.php": {
      "post": {
        "responses": {
          "default": {
            "description": "default",
            "schema": {
              "type": "string"
            }
          }
        },
        "summary": "Get Courses",
        "description": "Get a list of the Moodle Courses a user is enrolled in",
        "operationId": "GetCourses",
        "x-ms-visibility": "important",
        "parameters": [
          {
            "name": "Content-Type:",
            "in": "header",
            "required": false,
            "type": "string"
          },
          {
            "name": "Accept:",
            "in": "header",
            "required": false,
            "type": "string"
          },
          {
            "name": "body",
            "in": "body",
            "required": false,
            "schema": {
              "type": "string"
            }
          }
        ]
      }
    }
  },
  "definitions": {},
  "parameters": {},
  "responses": {},
  "securityDefinitions": {
    "api_key": {
      "type": "apiKey",
      "in": "query",
      "name": "wstoken"
    }
  },
  "security": [],
  "tags": []
}